{
    "extracted_text": "Heading\nName: ABC\nDate: 7/05/14 Age: 3o0yrs.\nSex: female\nDiagnosis: Idiopathic Parkinsonism\nTab Levodopa 1oomg\nTab Carbidopa 25mg\n2 tablets by mouth 3 times daily for one month .\nTake with food.\nDr. XYZ\nAssistant Prof. Neurology,\nReg. No. 345\n",
    "category": "Prescription",
    "summary": "Sex: female\nDiagnosis: Idiopathic Parkinsonism\nTab Levodopa 1oomg\nTab Carbidopa 25mg\n2 tablets by mouth 3 times daily for one month .\n Heading\nName: ABC\nDate: 7/05/14 Age: 3o0yrs.\n Dr. XYZ\nAssistant Prof. Neurology,\nReg.",
    "hospital": "Not found",
    "doctor": "Not found",
    "date": "7/05/14"
}